mssspy/__init__.py
mssspy/base_readers.py
mssspy/exceptions.py
mssspy/faster_reader.py
mssspy/index.py
mssspy/sample.py
mssspy/slow_reader.py
mssspy/utils.py
mssspy-0.1.0b2.dist-info/METADATA
mssspy-0.1.0b2.dist-info/WHEEL
mssspy-0.1.0b2.dist-info/top_level.txt
mssspy-0.1.0b2.dist-info/RECORD
