Metadata-Version: 2.1
Name: mssspy
Version: 0.1.0b2
Summary: A Python reader (and eventually writer) for ms files
Home-page: https://gitlab.com/mlgenetics/mssspy
Author: E. Madison Bray
Maintainer-email: embray@lri.fr
License: UNKNOWN
Platform: UNKNOWN
Classifier: Development Status :: 4 - Beta
Classifier: Intended Audience :: Science/Research
Classifier: Programming Language :: Python :: 3.7
Classifier: Topic :: Scientific/Engineering :: Bio-Informatics
Requires-Python: >=3.7
Requires-Dist: numpy
Provides-Extra: tests
Requires-Dist: pytest ; extra == 'tests'
Requires-Dist: pytest-flake8 ; extra == 'tests'
Requires-Dist: pytest-mypy ; extra == 'tests'
